LICENSE.md
MANIFEST.in
README.md
pyproject.toml
setup.py
src/pycatsearch_qt/__init__.py
src/pycatsearch_qt/__main__.py
src/pycatsearch_qt/_version.py
src/pycatsearch_qt/about_dialog.py
src/pycatsearch_qt/catalog_file_dialog.py
src/pycatsearch_qt/catalog_info.py
src/pycatsearch_qt/download_dialog.py
src/pycatsearch_qt/file_dialog.py
src/pycatsearch_qt/float_spinbox.py
src/pycatsearch_qt/found_lines_model.py
src/pycatsearch_qt/frequency_box.py
src/pycatsearch_qt/html_style_delegate.py
src/pycatsearch_qt/menu_bar.py
src/pycatsearch_qt/open_file_path_entry.py
src/pycatsearch_qt/preferences.py
src/pycatsearch_qt/save_catalog_waiting_screen.py
src/pycatsearch_qt/selectable_label.py
src/pycatsearch_qt/settings.py
src/pycatsearch_qt/substance_info.py
src/pycatsearch_qt/substances_box.py
src/pycatsearch_qt/titled_list_widget.py
src/pycatsearch_qt/ui.py
src/pycatsearch_qt/update_dialog.py
src/pycatsearch_qt/url_label.py
src/pycatsearch_qt/utils.py
src/pycatsearch_qt/waiting_screen.py
src/pycatsearch_qt.egg-info/PKG-INFO
src/pycatsearch_qt.egg-info/SOURCES.txt
src/pycatsearch_qt.egg-info/dependency_links.txt
src/pycatsearch_qt.egg-info/entry_points.txt
src/pycatsearch_qt.egg-info/requires.txt
src/pycatsearch_qt.egg-info/top_level.txt
src/pycatsearch_qt/catalog_wizard/__init__.py
src/pycatsearch_qt/catalog_wizard/download_confirmation_page.py
src/pycatsearch_qt/catalog_wizard/progress_page.py
src/pycatsearch_qt/catalog_wizard/settings_page.py
src/pycatsearch_qt/catalog_wizard/summary_page.py
src/pycatsearch_qt/i18n/de.qm
src/pycatsearch_qt/i18n/fr.qm
src/pycatsearch_qt/i18n/ru.qm